upload-insert-tools/__init__.py
upload-insert-tools/concurrent_insert.py
upload_insert_tools/__init__.py
upload_insert_tools/concurrent_insert.py
upload_insert_tools-0.3.dist-info/METADATA
upload_insert_tools-0.3.dist-info/WHEEL
upload_insert_tools-0.3.dist-info/top_level.txt
upload_insert_tools-0.3.dist-info/RECORD
