Metadata-Version: 2.1
Name: upload-insert-tools
Version: 0.3
Summary: upload log to flask logger
Home-page: https://flask-logger.herokuapp.com/
Author: Gal Metzer / Dor Genosar
Author-email: gal.metzer@gmail.com
License: apache
Platform: UNKNOWN
Requires-Dist: requests
